rotations/__init__.py
rotations/frames.py
rotations/rotations.py
rotations-0.0.2.dist-info/LICENSE
rotations-0.0.2.dist-info/WHEEL
rotations-0.0.2.dist-info/METADATA
rotations-0.0.2.dist-info/RECORD
